app/__init__.py
app/main.py
app/utils.py
cadproxdk-4.1.dist-info/LICENSE
cadproxdk-4.1.dist-info/METADATA
cadproxdk-4.1.dist-info/WHEEL
cadproxdk-4.1.dist-info/entry_points.txt
cadproxdk-4.1.dist-info/top_level.txt
cadproxdk-4.1.dist-info/RECORD
