Metadata-Version: 2.1
Name: cadproxdk
Version: 4.1
Summary: A tool to manage Caddy reverse proxy configurations with Cloudflare DNS.
Home-page: https://github.com/yourusername/cadproxdk
Author: Piotr Tamu (Thriveroute)
Author-email: your.email@example.com
Classifier: Programming Language :: Python :: 3
Classifier: License :: OSI Approved :: MIT License
Classifier: Operating System :: OS Independent
Requires-Python: >=3.11
License-File: LICENSE
Requires-Dist: requests ==2.31.0
Requires-Dist: dnspython ==2.6.1
Requires-Dist: boto3 ==1.34.112
Requires-Dist: python-dotenv ==1.0.1
Requires-Dist: twine ==4.0.2
